{"_invocation_id": "26810ee6-f765-483e-b0e8-f7ee29f44b8e", "linked": {"0": {"name": "model.across_analytics.get_token_decimals", "type": "model"}, "1": {"name": "model.across_analytics.rescale_amount", "type": "model"}, "2": {"name": "model.across_analytics.stg_arbitrum__refunds", "type": "model", "succ": [13]}, "3": {"name": "model.across_analytics.stg_ethereum__refunds", "type": "model", "succ": [13]}, "4": {"name": "model.across_analytics.stg_hyperevm__refunds", "type": "model", "succ": [13]}, "5": {"name": "model.across_analytics.stg_linea__refunds", "type": "model", "succ": [13]}, "6": {"name": "model.across_analytics.stg_monad__refunds", "type": "model", "succ": [13]}, "7": {"name": "model.across_analytics.stg_polygon__refunds", "type": "model", "succ": [13]}, "8": {"name": "model.across_analytics.stg_unichain__refunds", "type": "model", "succ": [13]}, "9": {"name": "model.across_analytics.stg_worldchain__refunds", "type": "model", "succ": [13]}, "10": {"name": "model.across_analytics.get_token_decimals_by_chain_id", "type": "model"}, "11": {"name": "model.across_analytics.stg_arbitrum__fills", "type": "model", "succ": [15]}, "12": {"name": "seed.across_analytics.token_metadata", "type": "seed", "succ": [11, 13, 27, 30, 24, 25, 31, 28, 29, 26, 17, 19, 21, 18, 16, 22, 20]}, "13": {"name": "model.across_analytics.int_unified_refunds", "type": "model", "succ": [14]}, "14": {"name": "model.across_analytics.int_unified_refunds_expanded", "type": "model"}, "15": {"name": "model.across_analytics.int_unified_fills", "type": "model", "succ": [33]}, "16": {"name": "model.across_analytics.stg_ethereum__fills", "type": "model", "succ": [15]}, "17": {"name": "model.across_analytics.stg_polygon__fills", "type": "model", "succ": [15]}, "18": {"name": "model.across_analytics.stg_linea__fills", "type": "model", "succ": [15]}, "19": {"name": "model.across_analytics.stg_worldchain__fills", "type": "model", "succ": [15]}, "20": {"name": "model.across_analytics.stg_unichain__fills", "type": "model", "succ": [15]}, "21": {"name": "model.across_analytics.stg_hyperevm__fills", "type": "model", "succ": [15]}, "22": {"name": "model.across_analytics.stg_monad__fills", "type": "model", "succ": [15]}, "23": {"name": "model.across_analytics.int_unified_deposits", "type": "model", "succ": [33]}, "24": {"name": "model.across_analytics.stg_arbitrum__deposits", "type": "model", "succ": [23]}, "25": {"name": "model.across_analytics.stg_ethereum__deposits", "type": "model", "succ": [23]}, "26": {"name": "model.across_analytics.stg_polygon__deposits", "type": "model", "succ": [23]}, "27": {"name": "model.across_analytics.stg_linea__deposits", "type": "model", "succ": [23]}, "28": {"name": "model.across_analytics.stg_worldchain__deposits", "type": "model", "succ": [23]}, "29": {"name": "model.across_analytics.stg_unichain__deposits", "type": "model", "succ": [23]}, "30": {"name": "model.across_analytics.stg_hyperevm__deposits", "type": "model", "succ": [23]}, "31": {"name": "model.across_analytics.stg_monad__deposits", "type": "model", "succ": [23]}, "32": {"name": "model.across_analytics.rescale_output_amount", "type": "model"}, "33": {"name": "model.across_analytics.int_deposit_fill_matching", "type": "model"}}}